[
    {
        "model": "quiz.category",
        "pk": 1,
        "fields": {
            "name": "Science",
            "type": "NTR"
        }
    },
    {
        "model": "quiz.category",
        "pk": 2,
        "fields": {
            "name": "Mathematics",
            "type": "EXC"
        }
    },
    {
        "model": "quiz.category",
        "pk": 3,
        "fields": {
            "name": "History",
            "type": "NTR"
        }
    },
    {
        "model": "quiz.category",
        "pk": 4,
        "fields": {
            "name": "Geography",
            "type": "EXC"
        }
    },
    {
        "model": "quiz.category",
        "pk": 5,
        "fields": {
            "name": "Technology",
            "type": "NTR"
        }
    },
    {
        "model": "quiz.subcategory",
        "pk": 1,
        "fields": {
            "name": "Physics",
            "category": 1
        }
    },
    {
        "model": "quiz.subcategory",
        "pk": 2,
        "fields": {
            "name": "Algebra",
            "category": 2
        }
    },
    {
        "model": "quiz.subcategory",
        "pk": 3,
        "fields": {
            "name": "World History",
            "category": 3
        }
    },
    {
        "model": "quiz.subcategory",
        "pk": 4,
        "fields": {
            "name": "Continents",
            "category": 4
        }
    },
    {
        "model": "quiz.subcategory",
        "pk": 5,
        "fields": {
            "name": "Programming",
            "category": 5
        }
    },
    {
        "model": "quiz.quiz",
        "pk": 1,
        "fields": {
            "title": "Science Quiz",
            "subtitle": "Test your knowledge in science",
            "category_set": 1
        }
    },
    {
        "model": "quiz.quiz",
        "pk": 2,
        "fields": {
            "title": "Math Quiz",
            "subtitle": "Test your knowledge in mathematics",
            "category_set": 2
        }
    },
    {
        "model": "quiz.quiz",
        "pk": 3,
        "fields": {
            "title": "History Quiz",
            "subtitle": "Test your knowledge in history",
            "category_set": 3
        }
    },
    {
        "model": "quiz.quiz",
        "pk": 4,
        "fields": {
            "title": "Geography Quiz",
            "subtitle": "Test your knowledge in geography",
            "category_set": 4
        }
    },
    {
        "model": "quiz.quiz",
        "pk": 5,
        "fields": {
            "title": "Technology Quiz",
            "subtitle": "Test your knowledge in technology",
            "category_set": 5
        }
    },

    {
        "model": "quiz.question",
        "pk": 1,
        "fields": {
            "text": "What is the speed of light?",
            "quiz": 1,
            "theme": 1
        }
    },
    {
        "model": "quiz.question",
        "pk": 2,
        "fields": {
            "text": "Who developed the theory of relativity?",
            "quiz": 1,
            "theme": 1
        }
    },
    {
        "model": "quiz.question",
        "pk": 3,
        "fields": {
            "text": "What is the chemical symbol for water?",
            "quiz": 1,
            "theme": 1
        }
    },
    {
        "model": "quiz.question",
        "pk": 4,
        "fields": {
            "text": "What planet is known as the Red Planet?",
            "quiz": 1,
            "theme": 1
        }
    },
    {
        "model": "quiz.question",
        "pk": 5,
        "fields": {
            "text": "What is Newton's First Law of Motion?",
            "quiz": 1,
            "theme": 1
        }
    },

    {
        "model": "quiz.answer",
        "pk": 1,
        "fields": {
            "text": "299,792 km/s",
            "question": 1,
            "is_correct": true
        }
    },
    {
        "model": "quiz.answer",
        "pk": 2,
        "fields": {
            "text": "150,000 km/s",
            "question": 1,
            "is_correct": false
        }
    },
    {
        "model": "quiz.answer",
        "pk": 3,
        "fields": {
            "text": "Albert Einstein",
            "question": 2,
            "is_correct": true
        }
    },
    {
        "model": "quiz.answer",
        "pk": 4,
        "fields": {
            "text": "Isaac Newton",
            "question": 2,
            "is_correct": false
        }
    },
    {
        "model": "quiz.answer",
        "pk": 5,
        "fields": {
            "text": "H2O",
            "question": 3,
            "is_correct": true
        }
    },
    {
        "model": "quiz.answer",
        "pk": 6,
        "fields": {
            "text": "CO2",
            "question": 3,
            "is_correct": false
        }
    },
    {
        "model": "quiz.answer",
        "pk": 7,
        "fields": {
            "text": "Mars",
            "question": 4,
            "is_correct": true
        }
    },
    {
        "model": "quiz.answer",
        "pk": 8,
        "fields": {
            "text": "Jupiter",
            "question": 4,
            "is_correct": false
        }
    },
    {
        "model": "quiz.answer",
        "pk": 9,
        "fields": {
            "text": "An object in motion stays in motion unless acted upon by an external force.",
            "question": 5,
            "is_correct": true
        }
    },
    {
        "model": "quiz.answer",
        "pk": 10,
        "fields": {
            "text": "For every action, there is an equal and opposite reaction.",
            "question": 5,
            "is_correct": false
        }
    }
]
